python_todopago/__init__.py
python_todopago/clients.py
python_todopago/exceptions.py
python_todopago/helpers.py
python_todopago/iso4217.json
python_todopago/serializers.py
python_todopago-1.0.6.data/data/python_todopago/iso4217.json
tests/__init__.py
tests/conftest.py
tests/test_helpers.py
tests/test_pytp.py
python_todopago-1.0.6.dist-info/LICENSE
python_todopago-1.0.6.dist-info/METADATA
python_todopago-1.0.6.dist-info/WHEEL
python_todopago-1.0.6.dist-info/top_level.txt
python_todopago-1.0.6.dist-info/RECORD
