Metadata-Version: 2.1
Name: python-todopago
Version: 1.0.6
Summary: TodoPago modern SDK for python
Home-page: https://github.com/juanpsenn/python-todopago
Author: Juan Pablo Senn
Author-email: juanpsenn@gmail.com
License: MIT
Project-URL: Issue Tracker, https://github.com/juanpsenn/python-todopago/issues
Platform: UNKNOWN
Classifier: Intended Audience :: Developers
Classifier: License :: OSI Approved :: MIT License
Classifier: Operating System :: OS Independent
Classifier: Programming Language :: Python :: 3
Classifier: Programming Language :: Python :: 3.7
Classifier: Programming Language :: Python :: 3.8
Classifier: Programming Language :: Python :: 3.9
Classifier: Topic :: Software Development :: Libraries :: Python Modules
License-File: LICENSE
Requires-Dist: requests (>=2.25.0)
Requires-Dist: zeep (<5.0.0,>=4.0.0)
